README.md
setup.cfg
setup.py
dsbootcamp4/__init__.py
dsbootcamp4/hi.py
dsbootcamp4.egg-info/PKG-INFO
dsbootcamp4.egg-info/SOURCES.txt
dsbootcamp4.egg-info/dependency_links.txt
dsbootcamp4.egg-info/top_level.txt
dsbootcamp4/abtesting/__init__.py
dsbootcamp4/crm/__init__.py
dsbootcamp4/data_prep/__init__.py
dsbootcamp4/data_prep/data_prep.py
dsbootcamp4/eda/__init__.py
dsbootcamp4/eda/eda.py
dsbootcamp4/eda/hi.py
dsbootcamp4/recommendation/__init__.py
dsbootcamp4/time_series/__init__.py