Metadata-Version: 1.1
Name: dsbootcamp4
Version: 0.0.3
Summary: Data Science Tools
Home-page: https://github.com/mvahit/dsbootcamp4
Author: Vahit Keskin
Author-email: UNKNOWN
License: MIT
Keywords: data science,machine learning,bootcamp
Platform: UNKNOWN
Classifier: Development Status :: 4 - Beta
Classifier: License :: OSI Approved :: MIT License
Classifier: Programming Language :: Python :: 3.5
Classifier: Topic :: Scientific/Engineering
